{
  "slug": "kumareshwar-mahadev",
  "name": {
    "hi": "कुमारेश्वर महादेव",
    "en": "Kumareshwar Mahadev (84 Mahadevas)"
  },
  "deity": {
    "hi": "भगवान शिव / कुमार (कार्तिकेय)",
    "en": "Lord Shiva / Kumar (Kartikeya)"
  },
  "templeType": "Shiva",
  "locationArea": "Mahakal Area",
  "isFeatured": false,
  "establishedEra": {
    "hi": "पुरातन काल (स्कन्द पुराण संदर्भित)",
    "en": "Ancient era (referenced in Skanda Purana)"
  },
  "architectureStyle": "Paramara",
  "shortIntro": {
    "hi": "कुमारेश्वर महादेव उज्जैन की 84 महादेव श्रृंखला का एक पवित्र तीर्थ है, जहाँ भगवान शिव 'कुमार' अर्थात कार्तिकेय के स्वामी रूप में पूजित हैं। यह मंदिर महाकाल क्षेत्र में स्थित है और स्कन्द पुराण के अवन्ति खण्ड में वर्णित है। कार्तिकेय भक्तों के लिए यह स्थान विशेष महत्त्व रखता है।",
    "en": "Kumareshwar Mahadev is a sacred shrine in the 84 Mahadevas series of Ujjain, where Lord Shiva is venerated as the lord of Kumar (Kartikeya). Located in the Mahakal Area, it is described in the Avanti Khanda of the Skanda Purana. This site holds special significance for devotees of Kartikeya."
  },
  "history": {
    "hi": "स्कन्द पुराण के अवन्ति खण्ड में कुमारेश्वर महादेव को उज्जैन के 84 महादेवों में विशेष स्थान दिया गया है। पौराणिक मान्यता है कि भगवान कार्तिकेय (कुमार) ने यहाँ शिवलिंग की स्थापना की थी और अपने पिता शिव की आराधना की थी, इसीलिए इस लिंग का नाम 'कुमारेश्वर' पड़ा। महाकाल वन की परिधि में स्थित यह तीर्थ अवन्तिका के उन सप्त पवित्र क्षेत्रों का अंग है जहाँ शिव साक्षात विराजमान माने जाते हैं। परम्परागत तीर्थयात्री 84 महादेवों की परिक्रमा में इस मंदिर को महत्त्वपूर्ण पड़ाव मानते हैं। यह मंदिर उज्जैन की सनातन परम्परा और शैव संस्कृति का जीवंत प्रमाण है।",
    "en": "The Avanti Khanda of the Skanda Purana assigns a special place to Kumareshwar Mahadev among the 84 Mahadevas of Ujjain. According to legend, Lord Kartikeya (Kumar) himself installed the Shivalinga here and worshipped his father Shiva, hence the name Kumareshwar. This tirtha within the Mahakal forest is part of Avantika's sacred landscape where Shiva is believed to be eternally present. Traditional pilgrims consider this temple an important stop in the 84 Mahadevas circumambulation. The shrine stands as a living testament to Ujjain's Shaiva cultural heritage."
  },
  "darshanTimingSummary": {
    "hi": "लगभग प्रातः 6:00 – रात्रि 9:00",
    "en": "Approx. 6:00 AM – 9:00 PM"
  },
  "weeklyTiming": {
    "monday": {
      "hi": "लगभग प्रातः 6:00 – रात्रि 9:00",
      "en": "Approx. 6:00 AM – 9:00 PM"
    },
    "tuesday": {
      "hi": "लगभग प्रातः 6:00 – रात्रि 9:00",
      "en": "Approx. 6:00 AM – 9:00 PM"
    },
    "wednesday": {
      "hi": "लगभग प्रातः 6:00 – रात्रि 9:00",
      "en": "Approx. 6:00 AM – 9:00 PM"
    },
    "thursday": {
      "hi": "लगभग प्रातः 6:00 – रात्रि 9:00",
      "en": "Approx. 6:00 AM – 9:00 PM"
    },
    "friday": {
      "hi": "लगभग प्रातः 6:00 – रात्रि 9:00",
      "en": "Approx. 6:00 AM – 9:00 PM"
    },
    "saturday": {
      "hi": "लगभग प्रातः 6:00 – रात्रि 9:00",
      "en": "Approx. 6:00 AM – 9:00 PM"
    },
    "sunday": {
      "hi": "लगभग प्रातः 6:00 – रात्रि 9:00",
      "en": "Approx. 6:00 AM – 9:00 PM"
    }
  },
  "aartiTiming": {
    "hi": "लगभग प्रातः आरती 6:30 · संध्या आरती 7:00",
    "en": "Morning aarti 6:30 AM · Evening aarti 7:00 PM"
  },
  "entryFee": {
    "hi": "निःशुल्क",
    "en": "Free entry"
  },
  "address": {
    "hi": "महाकाल क्षेत्र, उज्जैन, मध्य प्रदेश 456006",
    "en": "Mahakal Area, Ujjain, Madhya Pradesh 456006"
  },
  "geo": {
    "lat": 23.1827,
    "lng": 75.7679
  },
  "photos": [
    "/images/mandirs/shiva-variety-8.jpg"
  ],
  "howToReach": {
    "hi": "यह मंदिर महाकालेश्वर ज्योतिर्लिंग से लगभग 0.4 किमी की दूरी पर स्थित है। उज्जैन रेलवे स्टेशन से ऑटो या रिक्शा द्वारा लगभग 10-15 मिनट में पहुँचा जा सकता है।",
    "en": "The temple is approximately 0.4 km from Mahakaleshwar Jyotirlinga. It can be reached from Ujjain Railway Station by auto or rickshaw in about 10-15 minutes."
  },
  "nearbyMandirs": [],
  "lastVerified": "2026-05-31",
  "primaryKeyword": {
    "hi": "कुमारेश्वर महादेव उज्जैन",
    "en": "Kumareshwar Mahadev Ujjain"
  }
}
